ipyaladin/__about__.py
ipyaladin/__init__.py
ipyaladin/widget.py
ipyaladin/elements/__init__.py
ipyaladin/elements/error_shape.py
ipyaladin/elements/marker.py
ipyaladin/static/widget.css
ipyaladin/static/widget.js
ipyaladin/utils/__init__.py
ipyaladin/utils/_coordinate_parser.py
ipyaladin/utils/_region_converter.py
ipyaladin/utils/exceptions.py
ipyaladin-0.6.0.dist-info/METADATA
ipyaladin-0.6.0.dist-info/WHEEL
ipyaladin-0.6.0.dist-info/licenses/LICENSE.md
ipyaladin-0.6.0.dist-info/RECORD
