Metadata-Version: 2.4
Name: ipyaladin
Version: 0.6.0
License-Expression: BSD-3-Clause
License-File: LICENSE.md
Requires-Python: >=3.9
Requires-Dist: anywidget
Requires-Dist: astropy
Provides-Extra: dev
Requires-Dist: jupyterlab; extra == 'dev'
Requires-Dist: nbconvert; extra == 'dev'
Requires-Dist: pytest; extra == 'dev'
Requires-Dist: ruff; extra == 'dev'
Requires-Dist: watchfiles; extra == 'dev'
Provides-Extra: docs
Requires-Dist: autoapi; extra == 'docs'
Requires-Dist: jupyterlab; extra == 'docs'
Requires-Dist: myst-parser; extra == 'docs'
Requires-Dist: nbsphinx; extra == 'docs'
Requires-Dist: numpydoc; extra == 'docs'
Requires-Dist: pydata-sphinx-theme; extra == 'docs'
Requires-Dist: sphinx; extra == 'docs'
Requires-Dist: sphinx-autoapi>=3.0.0; extra == 'docs'
Requires-Dist: sphinx-collections; extra == 'docs'
Requires-Dist: sphinx-copybutton; extra == 'docs'
Requires-Dist: sphinx-gallery; extra == 'docs'
Provides-Extra: notebooks
Requires-Dist: requests; extra == 'notebooks'
Provides-Extra: recommended
Requires-Dist: astroquery>=0.4.8; extra == 'recommended'
Requires-Dist: mocpy; extra == 'recommended'
Requires-Dist: regions; extra == 'recommended'
